image_processing/__init__.py
image_processing/processing/__init__.py
image_processing/processing/combination.py
image_processing/processing/transformation.py
image_processing/utils/__init__.py
image_processing/utils/io.py
image_processing/utils/plot.py
Pacote_de_processamento_de_imagens_Pypi-0.0.1.dist-info/METADATA
Pacote_de_processamento_de_imagens_Pypi-0.0.1.dist-info/WHEEL
Pacote_de_processamento_de_imagens_Pypi-0.0.1.dist-info/top_level.txt
Pacote_de_processamento_de_imagens_Pypi-0.0.1.dist-info/RECORD
